setup.cfg
setup.py
python_skiplist.egg-info/PKG-INFO
python_skiplist.egg-info/SOURCES.txt
python_skiplist.egg-info/dependency_links.txt
python_skiplist.egg-info/top_level.txt
skiplist/__init__.py
skiplist/sortedsetobject.c