Metadata-Version: 1.1
Name: python-skiplist
Version: 0.1
Summary: SortedSet and SortedDict implementation by using skiplist
Home-page: https://github.com/sepeth/python-skiplist
Author: Doğan Çeçen
Author-email: sepeth@gmail.com
License: UNKNOWN
Platform: UNKNOWN
Classifier: Development Status :: 3 - Alpha
Classifier: Intended Audience :: Developers
Classifier: License :: OSI Approved :: Python Software Foundation License
Classifier: Programming Language :: Python :: 3.4
Classifier: Programming Language :: Python :: 3.3
Classifier: Programming Language :: Python :: 3
Classifier: Programming Language :: Python :: 2.7
